ml3_drift/__init__.py
ml3_drift/py.typed
ml3_drift/analysis/__init__.py
ml3_drift/analysis/report.py
ml3_drift/analysis/analyzer/__init__.py
ml3_drift/analysis/analyzer/base.py
ml3_drift/analysis/analyzer/batch.py
ml3_drift/analysis/analyzer/stream.py
ml3_drift/callbacks/__init__.py
ml3_drift/callbacks/base.py
ml3_drift/enums/__init__.py
ml3_drift/enums/monitoring.py
ml3_drift/exceptions/__init__.py
ml3_drift/exceptions/monitoring.py
ml3_drift/huggingface/__init__.py
ml3_drift/huggingface/drift_detection_pipeline.py
ml3_drift/models/__init__.py
ml3_drift/models/monitoring.py
ml3_drift/monitoring/__init__.py
ml3_drift/monitoring/algorithms/batch/bonferroni.py
ml3_drift/monitoring/algorithms/batch/chi_square.py
ml3_drift/monitoring/algorithms/batch/ks.py
ml3_drift/monitoring/algorithms/online/adwin.py
ml3_drift/monitoring/algorithms/online/kswin.py
ml3_drift/monitoring/algorithms/online/page_hinkley.py
ml3_drift/monitoring/base/base.py
ml3_drift/monitoring/base/base_multivariate.py
ml3_drift/monitoring/base/base_univariate.py
ml3_drift/monitoring/base/batch_monitoring_algorithm.py
ml3_drift/monitoring/base/online_monitorning_algorithm.py
ml3_drift/sklearn/__init__.py
ml3_drift/sklearn/base.py
ml3_drift-0.0.5.dist-info/METADATA
ml3_drift-0.0.5.dist-info/WHEEL
ml3_drift-0.0.5.dist-info/licenses/LICENSE
ml3_drift-0.0.5.dist-info/RECORD
