Metadata-Version: 2.4
Name: ml3-drift
Version: 0.0.5
Summary: Easy-to-embed drift detectors
Author-email: ML cube <giovanni.giacometti@mlcube.com>
License: Apache-2.0
License-File: LICENSE
Requires-Python: <3.14,>=3.10
Requires-Dist: scipy>=1.15.3
Provides-Extra: huggingface
Requires-Dist: transformers[torch]>=4.52.3; extra == 'huggingface'
Provides-Extra: pandas
Requires-Dist: pandas>=2.2.3; extra == 'pandas'
Provides-Extra: polars
Requires-Dist: polars>=1.31.0; extra == 'polars'
Provides-Extra: river
Requires-Dist: river>=0.22.0; extra == 'river'
Provides-Extra: sklearn
Requires-Dist: scikit-learn>=1.6.1; extra == 'sklearn'
